slackpdb
